tiny_model_profiler/__init__.py
tiny_model_profiler/profiler.py
tiny_model_profiler-0.3.1.dist-info/LICENSE.txt
tiny_model_profiler-0.3.1.dist-info/METADATA
tiny_model_profiler-0.3.1.dist-info/WHEEL
tiny_model_profiler-0.3.1.dist-info/top_level.txt
tiny_model_profiler-0.3.1.dist-info/RECORD
