Metadata-Version: 2.1
Name: tiny-model-profiler
Version: 0.3.1
Summary: Lightweight PyTorch/TensorFlow model profiler
Author: Mahika Shah
Author-email: mahikasha1@gmail.com
Requires-Python: >=3.7
License-File: LICENSE.txt
Requires-Dist: torch >=1.7.0
Requires-Dist: torchinfo >=1.7.0
